README.md
requirements.txt
setup.py
cvfinetune/__init__.py
cvfinetune/_version.py
cvfinetune/dataset.py
cvfinetune.egg-info/PKG-INFO
cvfinetune.egg-info/SOURCES.txt
cvfinetune.egg-info/dependency_links.txt
cvfinetune.egg-info/not-zip-safe
cvfinetune.egg-info/requires.txt
cvfinetune.egg-info/top_level.txt
cvfinetune/finetuner/__init__.py
cvfinetune/finetuner/base.py
cvfinetune/finetuner/factory.py
cvfinetune/finetuner/mpi.py
cvfinetune/finetuner/mixins/__init__.py
cvfinetune/finetuner/mixins/base.py
cvfinetune/finetuner/mixins/classifier.py
cvfinetune/finetuner/mixins/dataset.py
cvfinetune/finetuner/mixins/iterator.py
cvfinetune/finetuner/mixins/model.py
cvfinetune/finetuner/mixins/optimizer.py
cvfinetune/finetuner/mixins/trainer.py
cvfinetune/parser/__init__.py
cvfinetune/parser/base.py
cvfinetune/parser/dataset_args.py
cvfinetune/parser/model_args.py
cvfinetune/parser/training_args.py
cvfinetune/parser/utils.py
cvfinetune/training/__init__.py
cvfinetune/training/extensions/__init__.py
cvfinetune/training/extensions/gc_collect.py
cvfinetune/training/extensions/reporters/__init__.py
cvfinetune/training/extensions/reporters/base.py
cvfinetune/training/extensions/reporters/sacred.py
cvfinetune/training/extensions/reporters/wandb.py
cvfinetune/training/loss/__init__.py
cvfinetune/training/loss/smoothed_cross_entropy.py
cvfinetune/training/trainer/__init__.py
cvfinetune/training/trainer/alpha_pooling.py
cvfinetune/training/trainer/base.py
cvfinetune/utils/__init__.py
cvfinetune/utils/logging.py
cvfinetune/utils/mpi.py
cvfinetune/utils/sacred/__init__.py
cvfinetune/utils/sacred/experiment.py
cvfinetune/utils/sacred/plotter.py